odoo/addons/module_analysis/README.rst
odoo/addons/module_analysis/__init__.py
odoo/addons/module_analysis/__manifest__.py
odoo/addons/module_analysis/data/ir_config_parameter.xml
odoo/addons/module_analysis/data/ir_cron.xml
odoo/addons/module_analysis/data/ir_module_type.xml
odoo/addons/module_analysis/data/ir_module_type_rule.xml
odoo/addons/module_analysis/i18n/it.po
odoo/addons/module_analysis/i18n/module_analysis.pot
odoo/addons/module_analysis/i18n/zh_CN.po
odoo/addons/module_analysis/models/__init__.py
odoo/addons/module_analysis/models/ir_module_author.py
odoo/addons/module_analysis/models/ir_module_module.py
odoo/addons/module_analysis/models/ir_module_type.py
odoo/addons/module_analysis/models/ir_module_type_rule.py
odoo/addons/module_analysis/readme/CONFIGURE.rst
odoo/addons/module_analysis/readme/CONTRIBUTORS.rst
odoo/addons/module_analysis/readme/DESCRIPTION.rst
odoo/addons/module_analysis/readme/INSTALL.rst
odoo/addons/module_analysis/readme/USAGE.rst
odoo/addons/module_analysis/security/ir.model.access.csv
odoo/addons/module_analysis/static/description/add_module_type_rules.png
odoo/addons/module_analysis/static/description/analysis_pie.png
odoo/addons/module_analysis/static/description/analysis_pivot.png
odoo/addons/module_analysis/static/description/base_module_update.png
odoo/addons/module_analysis/static/description/config_parameters.png
odoo/addons/module_analysis/static/description/default_module_type_rules.png
odoo/addons/module_analysis/static/description/icon.png
odoo/addons/module_analysis/static/description/index.html
odoo/addons/module_analysis/static/description/installed_modules_by_types.png
odoo/addons/module_analysis/static/description/module_authors.png
odoo/addons/module_analysis/static/description/module_form.png
odoo/addons/module_analysis/static/description/module_types.png
odoo/addons/module_analysis/tests/__init__.py
odoo/addons/module_analysis/tests/test_module.py
odoo/addons/module_analysis/views/menu.xml
odoo13_addon_module_analysis-13.0.1.1.3.dist-info/METADATA
odoo13_addon_module_analysis-13.0.1.1.3.dist-info/WHEEL
odoo13_addon_module_analysis-13.0.1.1.3.dist-info/top_level.txt
odoo13_addon_module_analysis-13.0.1.1.3.dist-info/RECORD
