Metadata-Version: 2.1
Name: odoo13-addon-module_analysis
Version: 13.0.1.1.3
Summary: Add analysis tools regarding installed modules to know which installed modules comes from Odoo Core, OCA, or are custom modules
Home-page: https://github.com/OCA/server-tools
Author: GRAP, Odoo Community Association (OCA)
Author-email: support@odoo-community.org
License: AGPL-3
Classifier: Programming Language :: Python
Classifier: Framework :: Odoo
Classifier: Framework :: Odoo :: 13.0
Classifier: License :: OSI Approved :: GNU Affero General Public License v3
Requires-Python: >=3.5
Requires-Dist: odoo<13.1dev,>=13.0a
Requires-Dist: pygount
